datamaker_faker/__about__.py
datamaker_faker/__init__.py
datamaker_faker/core/__init__.py
datamaker_faker/core/faker.py
datamaker_faker/core/field.py
datamaker_faker/data/city.csv
datamaker_faker/data/country.csv
datamaker_faker/data/first_name.csv
datamaker_faker/data/last_name.csv
datamaker_faker/data/sex.csv
datamaker_faker/utils/__init__.py
datamaker_faker/utils/data_folder.py
datamaker_faker/utils/helpers.py
datamaker_faker/utils/time.py
datamaker_faker-0.0.1.dist-info/METADATA
datamaker_faker-0.0.1.dist-info/WHEEL
datamaker_faker-0.0.1.dist-info/licenses/LICENSE.txt
datamaker_faker-0.0.1.dist-info/RECORD
