Metadata-Version: 2.3
Name: datamaker-faker
Version: 0.0.1
Summary: A python lib for data generation
Project-URL: Documentation, https://github.com/automators-com/datamaker-faker#readme
Project-URL: Issues, https://github.com/automators-com/datamaker-faker/issues
Project-URL: Source, https://github.com/automators-com/datamaker-faker
Author-email: Ratul Maharaj <56479869+RatulMaharaj@users.noreply.github.com>
License-Expression: MIT
License-File: LICENSE.txt
Keywords: data,faker,generate,synthetic
Classifier: Development Status :: 4 - Beta
Classifier: Programming Language :: Python
Classifier: Programming Language :: Python :: 3.8
Classifier: Programming Language :: Python :: 3.9
Classifier: Programming Language :: Python :: 3.10
Classifier: Programming Language :: Python :: 3.11
Classifier: Programming Language :: Python :: 3.12
Classifier: Programming Language :: Python :: Implementation :: CPython
Classifier: Programming Language :: Python :: Implementation :: PyPy
Requires-Python: >=3.8
Requires-Dist: numpy==1.26.4
Requires-Dist: pandas
